flows_get_brightest/__init__.py
flows_get_brightest/auth.py
flows_get_brightest/catalogs.py
flows_get_brightest/corner.py
flows_get_brightest/instruments.py
flows_get_brightest/observer.py
flows_get_brightest/plan.py
flows_get_brightest/plots.py
flows_get_brightest/run_get_brightest.py
flows_get_brightest/target.py
flows_get_brightest/tests.py
flows_get_brightest/utils.py
flows_get_brightest/version.py
flows_get_brightest-2.1.1.dist-info/entry_points.txt
flows_get_brightest-2.1.1.dist-info/LICENSE
flows_get_brightest-2.1.1.dist-info/WHEEL
flows_get_brightest-2.1.1.dist-info/METADATA
flows_get_brightest-2.1.1.dist-info/RECORD
