Metadata-Version: 2.1
Name: flows_get_brightest
Version: 2.1.1
Summary: Helper script for getting the brightest star in a Hawk-I (or other)
Author-email: Emir Karamehmetoglu <emir.k@phys.au.dk>
Requires-Python: >=3.10
Classifier: License :: OSI Approved :: GNU General Public License v3 or later (GPLv3+)
Requires-Dist: requests
Requires-Dist: tendrils
Requires-Dist: astropy>=2.3.1
Requires-Dist: numpy>=1.19.1
Requires-Dist: regions
Requires-Dist: astroquery>=0.4.5
Requires-Dist: matplotlib
Requires-Dist: pytest >= 7.1.1 ; extra == "test"
Project-URL: Home, https://github.com/SNflows/flows-tools/
Provides-Extra: test
